{"utility_component_template":[{"key":"BIO_DRIVE","hidden":true,"size":"small","icon":"GFX_ship_part_warp_drive_1","icon_frame":1,"power":0,"ftl":true,"component_set":"ftl_components"},{"key":"BIO_PROPULSION","hidden":true,"size":"small","icon":"GFX_ship_part_thruster_1","icon_frame":1,"power":0,"component_set":"thruster_components"},{"key":"BIO_SENSORS","hidden":true,"size":"small","icon":"GFX_ship_part_sensor_2","icon_frame":1,"power":0,"sensor_range":2,"hyperlane_range":4,"component_set":"sensor_components"},{"key":"GUARDIAN_DRIVE","hidden":true,"size":"small","icon":"GFX_ship_part_warp_drive_3","icon_frame":1,"power":0,"ftl":true,"jumpdrive":true,"ship_modifier":{"ship_windup_mult":-0.8},"component_set":"ftl_components"},{"key":"GUARDIAN_PROPULSION","hidden":true,"size":"small","icon":"GFX_ship_part_thruster_4","icon_frame":1,"power":0,"component_set":"thruster_components"},{"key":"GUARDIAN_SENSORS","hidden":true,"size":"small","icon":"GFX_ship_part_sensor_4","icon_frame":1,"power":0,"sensor_range":4,"hyperlane_range":8,"component_set":"sensor_components"}]}